tests/__init__.py
tests/test_policy.py
tests/test_policy_simulator.py
tests/test_transition_simulator.py
tfrddlsim/__init__.py
tfrddlsim/policy/__init__.py
tfrddlsim/policy/abstract_policy.py
tfrddlsim/policy/default_policy.py
tfrddlsim/policy/random_policy.py
tfrddlsim/simulation/__init__.py
tfrddlsim/simulation/policy_simulator.py
tfrddlsim/simulation/transition_simulator.py
tfrddlsim/viz/__init__.py
tfrddlsim/viz/abstract_visualizer.py
tfrddlsim/viz/generic_visualizer.py
tfrddlsim/viz/navigation_visualizer.py
tfrddlsim/viz/plots/__init__.py
tfrddlsim/viz/plots/plot_navigation_policy
tfrddlsim-0.8.1.data/scripts/plot_navigation_policy
tfrddlsim-0.8.1.data/scripts/tfrddlsim
tfrddlsim-0.8.1.dist-info/LICENSE
tfrddlsim-0.8.1.dist-info/METADATA
tfrddlsim-0.8.1.dist-info/WHEEL
tfrddlsim-0.8.1.dist-info/top_level.txt
tfrddlsim-0.8.1.dist-info/RECORD
