Metadata-Version: 2.1
Name: tfrddlsim
Version: 0.8.1
Summary: RDDL2TensorFlow parser, compiler, and simulator.
Home-page: https://github.com/thiagopbueno/tf-rddlsim
Author: Thiago P. Bueno
Author-email: thiago.pbueno@gmail.com
License: GNU General Public License v3.0
Keywords: rddl,tensorflow,probabilistic-planning,mdp,simulator
Platform: UNKNOWN
Classifier: Development Status :: 3 - Alpha
Classifier: Environment :: Console
Classifier: Intended Audience :: Science/Research
Classifier: License :: OSI Approved :: GNU General Public License v3 (GPLv3)
Classifier: Natural Language :: English
Classifier: Operating System :: OS Independent
Classifier: Programming Language :: Python :: 3
Classifier: Topic :: Scientific/Engineering :: Artificial Intelligence
Requires-Python: >=3.6
Requires-Dist: tensorflow (<2.0.0)
Requires-Dist: matplotlib
Requires-Dist: typing
Requires-Dist: pyrddl
Requires-Dist: rddlgym
